setup.py
distributions_hippo/Binomialdistribution.py
distributions_hippo/Gaussiandistribution.py
distributions_hippo/Generaldistribution.py
distributions_hippo/__init__.py
distributions_hippo.egg-info/PKG-INFO
distributions_hippo.egg-info/SOURCES.txt
distributions_hippo.egg-info/dependency_links.txt
distributions_hippo.egg-info/not-zip-safe
distributions_hippo.egg-info/top_level.txt